local_tuya_ceiling_fan/__init__.py
local_tuya_ceiling_fan/device.py
local_tuya_ceiling_fan/domoticz/__init__.py
local_tuya_ceiling_fan/domoticz/install.py
local_tuya_ceiling_fan-2.0.0.dist-info/LICENSE
local_tuya_ceiling_fan-2.0.0.dist-info/METADATA
local_tuya_ceiling_fan-2.0.0.dist-info/WHEEL
local_tuya_ceiling_fan-2.0.0.dist-info/RECORD
